Ligare/GitHub/__init__.py
Ligare/GitHub/api.py
Ligare.GitHub-0.2.0.dist-info/LICENSE.md
Ligare.GitHub-0.2.0.dist-info/METADATA
Ligare.GitHub-0.2.0.dist-info/WHEEL
Ligare.GitHub-0.2.0.dist-info/top_level.txt
Ligare.GitHub-0.2.0.dist-info/RECORD
